aiohttp_oauth2_client/__init__.py
aiohttp_oauth2_client/middleware.py
aiohttp_oauth2_client/grant/__init__.py
aiohttp_oauth2_client/grant/authorization_code.py
aiohttp_oauth2_client/grant/client_credentials.py
aiohttp_oauth2_client/grant/common.py
aiohttp_oauth2_client/grant/device_code.py
aiohttp_oauth2_client/grant/resource_owner_password_credentials.py
aiohttp_oauth2_client/models/__init__.py
aiohttp_oauth2_client/models/errors.py
aiohttp_oauth2_client/models/grant.py
aiohttp_oauth2_client/models/pkce.py
aiohttp_oauth2_client/models/request.py
aiohttp_oauth2_client/models/response.py
aiohttp_oauth2_client/models/token.py
aiohttp_oauth2_client-2.0.1.dist-info/licenses/LICENSE
aiohttp_oauth2_client-2.0.1.dist-info/METADATA
aiohttp_oauth2_client-2.0.1.dist-info/WHEEL
aiohttp_oauth2_client-2.0.1.dist-info/top_level.txt
aiohttp_oauth2_client-2.0.1.dist-info/RECORD
