Metadata-Version: 2.4
Name: aiohttp-oauth2-client
Version: 2.0.1
Summary: OAuth2 support for aiohttp client
Author-email: Stijn Caerts <stijn.caerts@vito.be>
Project-URL: Homepage, https://github.com/VITObelgium/aiohttp-oauth2-client
Project-URL: Source, https://github.com/VITObelgium/aiohttp-oauth2-client.git
Project-URL: Issues, https://github.com/VITObelgium/aiohttp-oauth2-client/issues
Keywords: oauth2,aiohttp
Requires-Python: >=3.8
License-File: LICENSE
Requires-Dist: aiohttp~=3.12
Requires-Dist: pydantic~=2.7
Requires-Dist: rich
Provides-Extra: dev
Requires-Dist: pre-commit; extra == "dev"
Requires-Dist: ruff; extra == "dev"
Requires-Dist: pytest; extra == "dev"
Requires-Dist: pytest-asyncio; extra == "dev"
Requires-Dist: pytest-mock; extra == "dev"
Requires-Dist: nest-asyncio; extra == "dev"
Requires-Dist: aioresponses; extra == "dev"
Provides-Extra: docs
Requires-Dist: sphinx~=7.3.7; extra == "docs"
Requires-Dist: furo; extra == "docs"
Requires-Dist: autodoc_pydantic; extra == "docs"
Requires-Dist: sphinx-copybutton; extra == "docs"
Dynamic: license-file
